[
  {
    "name": "Bitcoin",
    "symbol": "₿",
    "rank": 1,
    "age": 5815,
    "color": "#fa9e32",
    "png32": "https://lcw.nyc3.cdn.digitaloceanspaces.com/production/currencies/32/btc.png",
    "png64": "https://lcw.nyc3.cdn.digitaloceanspaces.com/production/currencies/64/btc.png",
    "webp32": "https://lcw.nyc3.cdn.digitaloceanspaces.com/production/currencies/32/btc.webp",
    "webp64": "https://lcw.nyc3.cdn.digitaloceanspaces.com/production/currencies/64/btc.webp",
    "exchanges": 191,
    "markets": 2545,
    "pairs": 768,
    "categories": [],
    "allTimeHighUSD": 103157.36267401562,
    "circulatingSupply": 19790568,
    "totalSupply": 19790568,
    "maxSupply": 21000000,
    "links": {
      "website": "https://bitcoin.org",
      "whitepaper": "https://bitcoin.org/bitcoin.pdf",
      "twitter": null,
      "reddit": "https://reddit.com/r/bitcoin",
      "telegram": null,
      "discord": null,
      "medium": null,
      "instagram": null,
      "tiktok": null,
      "youtube": null,
      "linkedin": null,
      "twitch": null,
      "spotify": null,
      "naver": null,
      "wechat": null,
      "soundcloud": null
    },
    "code": "BTC",
    "rate": 102382.17047680142,
    "volume": 93341520056,
    "cap": 2026201306808,
    "delta": {
      "hour": 1.0392,
      "day": 1.067,
      "week": 1.0724,
      "month": 1.5046,
      "quarter": 1.8049,
      "year": 2.3312
    }
  },
  {
    "name": "Ethereum",
    "symbol": "Ξ",
    "rank": 2,
    "age": 3407,
    "color": "#282a2a",
    "png32": "https://lcw.nyc3.cdn.digitaloceanspaces.com/production/currencies/32/eth.png",
    "png64": "https://lcw.nyc3.cdn.digitaloceanspaces.com/production/currencies/64/eth.png",
    "webp32": "https://lcw.nyc3.cdn.digitaloceanspaces.com/production/currencies/32/eth.webp",
    "webp64": "https://lcw.nyc3.cdn.digitaloceanspaces.com/production/currencies/64/eth.webp",
    "exchanges": 363,
    "markets": 6415,
    "pairs": 3399,
    "categories": [
      "smart_contract_platforms"
    ],
    "allTimeHighUSD": 4861.28870081089,
    "circulatingSupply": 117885856,
    "totalSupply": 117885856,
    "maxSupply": null,
    "links": {
      "website": "https://ethereum.org/en/",
      "whitepaper": "https://ethereum.org/en/whitepaper",
      "twitter": "https://x.com/ethereum",
      "reddit": "https://reddit.com/r/ethereum",
      "telegram": null,
      "discord": "https://discord.com/invite/ethereum-org",
      "medium": null,
      "instagram": null,
      "tiktok": null,
      "youtube": null,
      "linkedin": null,
      "twitch": null,
      "spotify": null,
      "naver": null,
      "wechat": null,
      "soundcloud": null
    },
    "code": "ETH",
    "rate": 3865.4613613506385,
    "volume": 71426960175,
    "cap": 455683221417,
    "delta": {
      "hour": 1.0135,
      "day": 1.0546,
      "week": 1.0694,
      "month": 1.6027,
      "quarter": 1.6121,
      "year": 1.6865
    }
  },
  {
    "name": "Tether",
    "rank": 3,
    "age": 3570,
    "color": "#e9f4f4",
    "png32": "https://lcw.nyc3.cdn.digitaloceanspaces.com/production/currencies/32/usdt.png",
    "png64": "https://lcw.nyc3.cdn.digitaloceanspaces.com/production/currencies/64/usdt.png",
    "webp32": "https://lcw.nyc3.cdn.digitaloceanspaces.com/production/currencies/32/usdt.webp",
    "webp64": "https://lcw.nyc3.cdn.digitaloceanspaces.com/production/currencies/64/usdt.webp",
    "exchanges": 331,
    "markets": 20081,
    "pairs": 5023,
    "categories": [
      "stablecoins",
      "asset_backed_tokens"
    ],
    "allTimeHighUSD": 1.08372533074166,
    "circulatingSupply": 135691101232,
    "totalSupply": 135691101232,
    "maxSupply": null,
    "links": {
      "website": "https://tether.to/",
      "whitepaper": "https://assets.ctfassets.net/vyse88cgwfbl/5UWgHMvz071t2Cq5yTw5vi/c9798ea8db99311bf90ebe0810938b01/TetherWhitePaper.pdf",
      "twitter": "https://x.com/tether_to",
      "reddit": "https://reddit.com/r/Tether",
      "telegram": "https://t.me/OfficialTether",
      "discord": null,
      "medium": null,
      "instagram": "https://www.instagram.com/tether/",
      "tiktok": null,
      "youtube": null,
      "linkedin": "https://www.linkedin.com/company/tether/",
      "twitch": null,
      "spotify": null,
      "naver": null,
      "wechat": null,
      "soundcloud": null
    },
    "code": "USDT",
    "rate": 0.9988364083574608,
    "volume": 250944504445,
    "cap": 135533212200,
    "delta": {
      "hour": 0.9978,
      "day": 0.9982,
      "week": 0.9997,
      "month": 0.9988,
      "quarter": 1.0002,
      "year": 0.9985
    }
  },
  {
    "name": "XRP",
    "rank": 4,
    "age": 4140,
    "color": "#040404",
    "png32": "https://lcw.nyc3.cdn.digitaloceanspaces.com/production/currencies/32/xrp.png",
    "png64": "https://lcw.nyc3.cdn.digitaloceanspaces.com/production/currencies/64/xrp.png",
    "webp32": "https://lcw.nyc3.cdn.digitaloceanspaces.com/production/currencies/32/xrp.webp",
    "webp64": "https://lcw.nyc3.cdn.digitaloceanspaces.com/production/currencies/64/xrp.webp",
    "exchanges": 131,
    "markets": 467,
    "pairs": 228,
    "categories": [
      "smart_contract_platforms"
    ],
    "allTimeHighUSD": 3.91546307780967,
    "circulatingSupply": 57051491087,
    "totalSupply": 99986947886,
    "maxSupply": 100000000000,
    "links": {
      "website": "https://ripple.com/",
      "whitepaper": "https://interledger.org/interledger.pdf",
      "twitter": "https://twitter.com/Ripple",
      "reddit": "https://reddit.com/r/ripple",
      "telegram": "https://t.me/Ripple",
      "discord": null,
      "medium": null,
      "instagram": null,
      "tiktok": null,
      "youtube": null,
      "linkedin": null,
      "twitch": null,
      "spotify": null,
      "naver": null,
      "wechat": null,
      "soundcloud": null
    },
    "code": "XRP",
    "rate": 2.335708231737397,
    "volume": 19885299285,
    "cap": 133255637364,
    "delta": {
      "hour": 1.0351,
      "day": 0.9134,
      "week": 1.5987,
      "month": 4.6157,
      "quarter": 4.2837,
      "year": 3.7314
    }
  },
  {
    "name": "Solana",
    "rank": 5,
    "age": 1697,
    "color": "#7370e8",
    "png32": "https://lcw.nyc3.cdn.digitaloceanspaces.com/production/currencies/32/sol.png",
    "png64": "https://lcw.nyc3.cdn.digitaloceanspaces.com/production/currencies/64/sol.png",
    "webp32": "https://lcw.nyc3.cdn.digitaloceanspaces.com/production/currencies/32/sol.webp",
    "webp64": "https://lcw.nyc3.cdn.digitaloceanspaces.com/production/currencies/64/sol.webp",
    "exchanges": 99,
    "markets": 2351,
    "pairs": 1559,
    "categories": [
      "smart_contract_platforms"
    ],
    "allTimeHighUSD": 263.4273198583234,
    "circulatingSupply": 475356627,
    "totalSupply": 589565940,
    "maxSupply": null,
    "links": {
      "website": "https://solana.com/",
      "whitepaper": "https://solana.com/docs",
      "twitter": "https://x.com/solana",
      "reddit": "https://reddit.com/r/solana",
      "telegram": "https://t.me/solana",
      "discord": "https://discord.com/invite/kBbATFA7PW",
      "medium": "https://medium.com/solana-labs",
      "instagram": "https://www.instagram.com/solana_updates",
      "tiktok": null,
      "youtube": "https://youtube.com/@SolanaFndn",
      "linkedin": null,
      "twitch": null,
      "spotify": null,
      "naver": null,
      "wechat": null,
      "soundcloud": null
    },
    "code": "SOL",
    "rate": 233.81293183562227,
    "volume": 9907108859,
    "cap": 111144526626,
    "delta": {
      "hour": 1.0305,
      "day": 0.9847,
      "week": 0.9701,
      "month": 1.4725,
      "quarter": 1.7858,
      "year": 3.6818
    }
  },
  {
    "name": "BNB",
    "rank": 6,
    "age": 2689,
    "color": "#f4bc2c",
    "png32": "https://lcw.nyc3.cdn.digitaloceanspaces.com/production/currencies/32/bnb.png",
    "png64": "https://lcw.nyc3.cdn.digitaloceanspaces.com/production/currencies/64/bnb.png",
    "webp32": "https://lcw.nyc3.cdn.digitaloceanspaces.com/production/currencies/32/bnb.webp",
    "webp64": "https://lcw.nyc3.cdn.digitaloceanspaces.com/production/currencies/64/bnb.webp",
    "exchanges": 138,
    "markets": 4250,
    "pairs": 3230,
    "categories": [
      "cex",
      "smart_contract_platforms"
    ],
    "allTimeHighUSD": 795.3440808257874,
    "circulatingSupply": 148930232,
    "totalSupply": 148930232,
    "maxSupply": 200000000,
    "links": {
      "website": "https://www.binance.com/en/bnb?ref=Y6TC8MN4",
      "whitepaper": "https://academy.binance.com/en/articles/what-is-bnb?ref=Y6TC8MN4",
      "twitter": "https://x.com/binance",
      "reddit": "https://reddit.com/r/binance",
      "telegram": "https://t.me/BinanceExchange",
      "discord": "https://discord.com/invite/jE4wt8g2H2",
      "medium": "https://medium.com/@binance",
      "instagram": "https://instagram.com/Binance",
      "tiktok": "https://www.tiktok.com/@binance",
      "youtube": "https://www.youtube.com/binanceyoutube",
      "linkedin": "https://www.linkedin.com/company/binance",
      "twitch": null,
      "spotify": null,
      "naver": null,
      "wechat": null,
      "soundcloud": null
    },
    "code": "BNB",
    "rate": 713.5607744056309,
    "volume": 6995776399,
    "cap": 106270771678,
    "delta": {
      "hour": 1.0129,
      "day": 0.9531,
      "week": 1.0996,
      "month": 1.2773,
      "quarter": 1.4103,
      "year": 3.0052
    }
  },
  {
    "name": "Dogecoin",
    "symbol": "Ɖ",
    "rank": 7,
    "age": 4007,
    "color": "#eee0b6",
    "png32": "https://lcw.nyc3.cdn.digitaloceanspaces.com/production/currencies/32/doge.png",
    "png64": "https://lcw.nyc3.cdn.digitaloceanspaces.com/production/currencies/64/doge.png",
    "webp32": "https://lcw.nyc3.cdn.digitaloceanspaces.com/production/currencies/32/doge.webp",
    "webp64": "https://lcw.nyc3.cdn.digitaloceanspaces.com/production/currencies/64/doge.webp",
    "exchanges": 126,
    "markets": 299,
    "pairs": 140,
    "categories": [
      "meme",
      "wallets",
      "charity"
    ],
    "allTimeHighUSD": 0.7371712183910056,
    "circulatingSupply": 132670764299,
    "totalSupply": 132670764299,
    "maxSupply": null,
    "links": {
      "website": "https://dogecoin.com/",
      "whitepaper": "https://dogecoin.com/dogepedia/",
      "twitter": "https://x.com/dogecoin",
      "reddit": "https://reddit.com/r/dogecoin",
      "telegram": null,
      "discord": "https://discord.com/invite/dogecoin",
      "medium": null,
      "instagram": null,
      "tiktok": null,
      "youtube": null,
      "linkedin": null,
      "twitch": null,
      "spotify": null,
      "naver": null,
      "wechat": null,
      "soundcloud": null
    },
    "code": "DOGE",
    "rate": 0.4334072954521011,
    "volume": 8611305842,
    "cap": 57500477140,
    "delta": {
      "hour": 1.0394,
      "day": 1.0447,
      "week": 1.0595,
      "month": 2.6673,
      "quarter": 4.383,
      "year": 4.581
    }
  },
  {
    "name": "Cardano",
    "rank": 8,
    "age": 2621,
    "color": "#226ed8",
    "png32": "https://lcw.nyc3.cdn.digitaloceanspaces.com/production/currencies/32/ada.png",
    "png64": "https://lcw.nyc3.cdn.digitaloceanspaces.com/production/currencies/64/ada.png",
    "webp32": "https://lcw.nyc3.cdn.digitaloceanspaces.com/production/currencies/32/ada.webp",
    "webp64": "https://lcw.nyc3.cdn.digitaloceanspaces.com/production/currencies/64/ada.webp",
    "exchanges": 100,
    "markets": 262,
    "pairs": 87,
    "categories": [
      "smart_contract_platforms"
    ],
    "allTimeHighUSD": 3.0939096930263132,
    "circulatingSupply": 37404996776,
    "totalSupply": 37404996776,
    "maxSupply": 45000000000,
    "links": {
      "website": "https://cardano.org/",
      "whitepaper": "https://www.cardanohub.org/en/academic-papers/",
      "twitter": "https://twitter.com/Cardano",
      "reddit": "https://reddit.com/r/cardano",
      "telegram": "https://t.me/cardano",
      "discord": null,
      "medium": null,
      "instagram": null,
      "tiktok": null,
      "youtube": null,
      "linkedin": null,
      "twitch": null,
      "spotify": null,
      "naver": null,
      "wechat": null,
      "soundcloud": null
    },
    "code": "ADA",
    "rate": 1.201984694671888,
    "volume": 3055278477,
    "cap": 44960233629,
    "delta": {
      "hour": 1.0549,
      "day": 0.9951,
      "week": 1.1937,
      "month": 3.6394,
      "quarter": 3.6798,
      "year": 2.831
    }
  },
  {
    "name": "USDC",
    "rank": 9,
    "age": 2249,
    "color": "#edf3f9",
    "png32": "https://lcw.nyc3.cdn.digitaloceanspaces.com/production/currencies/32/usdc.png",
    "png64": "https://lcw.nyc3.cdn.digitaloceanspaces.com/production/currencies/64/usdc.png",
    "webp32": "https://lcw.nyc3.cdn.digitaloceanspaces.com/production/currencies/32/usdc.webp",
    "webp64": "https://lcw.nyc3.cdn.digitaloceanspaces.com/production/currencies/64/usdc.webp",
    "exchanges": 295,
    "markets": 2393,
    "pairs": 1176,
    "categories": [
      "stablecoins",
      "asset_backed_tokens"
    ],
    "allTimeHighUSD": 1.087,
    "circulatingSupply": 40636144794,
    "totalSupply": 40636144794,
    "maxSupply": null,
    "links": {
      "website": "https://www.circle.com/en/usdc",
      "whitepaper": "https://www.circle.com/en/legal/mica-usdc-whitepaper",
      "twitter": "https://x.com/circle",
      "reddit": null,
      "telegram": null,
      "discord": "https://discord.com/invite/buildoncircle",
      "medium": null,
      "instagram": "https://www.instagram.com/teamcircle/",
      "tiktok": null,
      "youtube": "https://www.youtube.com/@BuildOnCircle",
      "linkedin": "https://www.linkedin.com/company/circle-internet-financial/",
      "twitch": null,
      "spotify": null,
      "naver": null,
      "wechat": null,
      "soundcloud": null
    },
    "code": "USDC",
    "rate": 0.9964407476209354,
    "volume": 11414699736,
    "cap": 40491510498,
    "delta": {
      "hour": 0.9973,
      "day": 0.9965,
      "week": 1.0004,
      "month": 0.9965,
      "quarter": 0.9984,
      "year": 0.9967
    }
  },
  {
    "name": "TRON",
    "rank": 10,
    "age": 2640,
    "color": "#c43429",
    "png32": "https://lcw.nyc3.cdn.digitaloceanspaces.com/production/currencies/32/trx.png",
    "png64": "https://lcw.nyc3.cdn.digitaloceanspaces.com/production/currencies/64/trx.png",
    "webp32": "https://lcw.nyc3.cdn.digitaloceanspaces.com/production/currencies/32/trx.webp",
    "webp64": "https://lcw.nyc3.cdn.digitaloceanspaces.com/production/currencies/64/trx.webp",
    "exchanges": 103,
    "markets": 237,
    "pairs": 49,
    "categories": [
      "storage",
      "smart_contract_platforms"
    ],
    "allTimeHighUSD": 0.43911345907206795,
    "circulatingSupply": 86364305772.35286,
    "totalSupply": 86284505298,
    "maxSupply": null,
    "links": {
      "website": "https://tron.network/",
      "whitepaper": "https://o836fhe91.qnssl.com/tron/whitebook/TronWhitepaper_en.pdf",
      "twitter": "https://twitter.com/trondao",
      "reddit": "https://reddit.com/r/Tronix",
      "telegram": "https://t.me/tronnetworkEN",
      "discord": "https://discord.com/invite/ezNzd9W",
      "medium": "https://tronfoundation.medium.com/",
      "instagram": "https://instagram.com/tronfoundation",
      "tiktok": null,
      "youtube": null,
      "linkedin": null,
      "twitch": null,
      "spotify": null,
      "naver": null,
      "wechat": null,
      "soundcloud": null
    },
    "code": "TRX",
    "rate": 0.32848412627154255,
    "volume": 9090102630,
    "cap": 28369303522,
    "delta": {
      "hour": 1.0005,
      "day": 0.8677,
      "week": 1.6441,
      "month": 2.0148,
      "quarter": 2.191,
      "year": 3.1088
    }
  },
  {
    "name": "Avalanche",
    "rank": 11,
    "age": 1534,
    "color": "#ec4343",
    "png32": "https://lcw.nyc3.cdn.digitaloceanspaces.com/production/currencies/32/avax.png",
    "png64": "https://lcw.nyc3.cdn.digitaloceanspaces.com/production/currencies/64/avax.png",
    "webp32": "https://lcw.nyc3.cdn.digitaloceanspaces.com/production/currencies/32/avax.webp",
    "webp64": "https://lcw.nyc3.cdn.digitaloceanspaces.com/production/currencies/64/avax.webp",
    "exchanges": 86,
    "markets": 446,
    "pairs": 209,
    "categories": [
      "smart_contract_platforms"
    ],
    "allTimeHighUSD": 146.465715882705,
    "circulatingSupply": 409353098,
    "totalSupply": 377752194,
    "maxSupply": 720000000,
    "links": {
      "website": "https://www.avax.network/",
      "whitepaper": "https://docs.avax.network/",
      "twitter": "https://twitter.com/avalancheavax",
      "reddit": "https://reddit.com/r/Avax",
      "telegram": "https://t.me/avalancheavax",
      "discord": "https://discord.com/invite/RwXY7P6",
      "medium": "https://medium.com/avalancheavax",
      "instagram": null,
      "tiktok": null,
      "youtube": null,
      "linkedin": null,
      "twitch": null,
      "spotify": null,
      "naver": null,
      "wechat": null,
      "soundcloud": null
    },
    "code": "AVAX",
    "rate": 51.383610146071604,
    "volume": 1953721513,
    "cap": 21034039999,
    "delta": {
      "hour": 1.0168,
      "day": 0.9941,
      "week": 1.1889,
      "month": 2.2524,
      "quarter": 2.3745,
      "year": 1.9595
    }
  },
  {
    "name": "Shiba Inu",
    "rank": 12,
    "age": 1400,
    "color": "#faa00d",
    "png32": "https://lcw.nyc3.cdn.digitaloceanspaces.com/production/currencies/32/shib.png",
    "png64": "https://lcw.nyc3.cdn.digitaloceanspaces.com/production/currencies/64/shib.png",
    "webp32": "https://lcw.nyc3.cdn.digitaloceanspaces.com/production/currencies/32/shib.webp",
    "webp64": "https://lcw.nyc3.cdn.digitaloceanspaces.com/production/currencies/64/shib.webp",
    "exchanges": 103,
    "markets": 175,
    "pairs": 51,
    "categories": [
      "meme",
      "metaverse",
      "nfts",
      "dex",
      "yield_farming"
    ],
    "allTimeHighUSD": 0.00008877244256117385,
    "circulatingSupply": 589224622655581,
    "totalSupply": 589508847396231,
    "maxSupply": null,
    "links": {
      "website": "https://shibatoken.com/",
      "whitepaper": "https://github.com/shytoshikusama/shibawoofpaper/blob/main/SHIBAINU_Ecosystem_WOOF_Paper.pdf",
      "twitter": "https://x.com/shibtoken",
      "reddit": "https://reddit.com/r/SHIBArmy",
      "telegram": "https://t.me/shibainuthedogecoinkiller",
      "discord": "https://discord.com/invite/shibatoken",
      "medium": "https://allhailtheshiba.medium.com",
      "instagram": "https://www.instagram.com/shibatoken_official/",
      "tiktok": null,
      "youtube": null,
      "linkedin": null,
      "twitch": null,
      "spotify": null,
      "naver": null,
      "wechat": null,
      "soundcloud": null
    },
    "code": "SHIB",
    "rate": 0.000031180002249471113,
    "volume": 3275253238,
    "cap": 18372025059,
    "delta": {
      "hour": 1.0039,
      "day": 1.0379,
      "week": 1.2148,
      "month": 1.801,
      "quarter": 2.3362,
      "year": 3.292
    }
  },
  {
    "name": "Toncoin",
    "rank": 13,
    "age": 1195,
    "color": "#048cd4",
    "png32": "https://lcw.nyc3.cdn.digitaloceanspaces.com/production/currencies/32/toncoin.png",
    "png64": "https://lcw.nyc3.cdn.digitaloceanspaces.com/production/currencies/64/toncoin.png",
    "webp32": "https://lcw.nyc3.cdn.digitaloceanspaces.com/production/currencies/32/toncoin.webp",
    "webp64": "https://lcw.nyc3.cdn.digitaloceanspaces.com/production/currencies/64/toncoin.webp",
    "exchanges": 37,
    "markets": 85,
    "pairs": 44,
    "categories": [
      "smart_contract_platforms",
      "social_media",
      "governance",
      "dns",
      "storage"
    ],
    "allTimeHighUSD": 98.783104434167,
    "circulatingSupply": 2549983756,
    "totalSupply": 5116691950,
    "maxSupply": null,
    "links": {
      "website": "https://ton.org/",
      "whitepaper": "https://ton.org/docs/",
      "twitter": "https://x.com/ton_blockchain",
      "reddit": "https://reddit.com/r/TONcoin",
      "telegram": "https://t.me/tonblockchain",
      "discord": null,
      "medium": null,
      "instagram": null,
      "tiktok": null,
      "youtube": null,
      "linkedin": "https://www.linkedin.com/company/ton-blockchain/",
      "twitch": null,
      "spotify": null,
      "naver": null,
      "wechat": null,
      "soundcloud": null
    },
    "code": "TONCOIN",
    "rate": 6.840183729909702,
    "volume": 414174754,
    "cap": 17442357399,
    "delta": {
      "hour": 1.0195,
      "day": 0.9978,
      "week": 1.0816,
      "month": 1.4749,
      "quarter": 1.4089,
      "year": 2.9244
    }
  },
  {
    "name": "Polkadot",
    "rank": 14,
    "age": 1564,
    "color": "#e4047c",
    "png32": "https://lcw.nyc3.cdn.digitaloceanspaces.com/production/currencies/32/dot.png",
    "png64": "https://lcw.nyc3.cdn.digitaloceanspaces.com/production/currencies/64/dot.png",
    "webp32": "https://lcw.nyc3.cdn.digitaloceanspaces.com/production/currencies/32/dot.webp",
    "webp64": "https://lcw.nyc3.cdn.digitaloceanspaces.com/production/currencies/64/dot.webp",
    "exchanges": 94,
    "markets": 169,
    "pairs": 39,
    "categories": [
      "smart_contract_platforms"
    ],
    "allTimeHighUSD": 55.06538188283951,
    "circulatingSupply": 1501010308,
    "totalSupply": 1525539137,
    "maxSupply": null,
    "links": {
      "website": "https://polkadot.com/",
      "whitepaper": "https://assets.polkadot.network/Polkadot-whitepaper.pdf",
      "twitter": "https://twitter.com/Polkadot",
      "reddit": "https://reddit.com/r/dot",
      "telegram": "https://t.me/PolkadotOfficial",
      "discord": "https://discord.com/invite/wGUDt2p",
      "medium": "https://medium.com/polkadot-network",
      "instagram": null,
      "tiktok": null,
      "youtube": "https://youtube.com/@PolkadotNetwork",
      "linkedin": null,
      "twitch": null,
      "spotify": null,
      "naver": null,
      "wechat": null,
      "soundcloud": null
    },
    "code": "DOT",
    "rate": 10.413993983738532,
    "volume": 2325159751,
    "cap": 15631512317,
    "delta": {
      "hour": 1.0314,
      "day": 1.0548,
      "week": 1.2633,
      "month": 2.7484,
      "quarter": 2.5727,
      "year": 1.7531
    }
  },
  {
    "name": "Chainlink",
    "rank": 15,
    "age": 2632,
    "color": "#365dd4",
    "png32": "https://lcw.nyc3.cdn.digitaloceanspaces.com/production/currencies/32/link.png",
    "png64": "https://lcw.nyc3.cdn.digitaloceanspaces.com/production/currencies/64/link.png",
    "webp32": "https://lcw.nyc3.cdn.digitaloceanspaces.com/production/currencies/32/link.webp",
    "webp64": "https://lcw.nyc3.cdn.digitaloceanspaces.com/production/currencies/64/link.webp",
    "exchanges": 166,
    "markets": 368,
    "pairs": 81,
    "categories": [
      "oracle",
      "token_bridges",
      "security",
      "analytics"
    ],
    "allTimeHighUSD": 52.85091701629316,
    "circulatingSupply": 626849970,
    "totalSupply": 1000000000,
    "maxSupply": 1000000000,
    "links": {
      "website": "https://chain.link/",
      "whitepaper": "https://research.chain.link/whitepaper-v2.pdf",
      "twitter": "https://x.com/chainlink",
      "reddit": "https://reddit.com/r/chainlink",
      "telegram": "https://t.me/chainlinkofficial",
      "discord": "https://discord.gg/aSK4zew",
      "medium": null,
      "instagram": null,
      "tiktok": null,
      "youtube": "https://www.youtube.com/@chainlink",
      "linkedin": null,
      "twitch": null,
      "spotify": null,
      "naver": null,
      "wechat": null,
      "soundcloud": null
    },
    "code": "LINK",
    "rate": 23.837812099036594,
    "volume": 3249278414,
    "cap": 14942731799,
    "delta": {
      "hour": 1.0175,
      "day": 0.998,
      "week": 1.3116,
      "month": 2.3,
      "quarter": 2.353,
      "year": 1.5092
    }
  },
  {
    "name": "Stellar",
    "rank": 16,
    "age": 3774,
    "color": "#040404",
    "png32": "https://lcw.nyc3.cdn.digitaloceanspaces.com/production/currencies/32/xlm.png",
    "png64": "https://lcw.nyc3.cdn.digitaloceanspaces.com/production/currencies/64/xlm.png",
    "webp32": "https://lcw.nyc3.cdn.digitaloceanspaces.com/production/currencies/32/xlm.webp",
    "webp64": "https://lcw.nyc3.cdn.digitaloceanspaces.com/production/currencies/64/xlm.webp",
    "exchanges": 74,
    "markets": 157,
    "pairs": 42,
    "categories": [
      "smart_contract_platforms"
    ],
    "allTimeHighUSD": 0.921644339265009,
    "circulatingSupply": 30118455127,
    "totalSupply": 50001786911,
    "maxSupply": null,
    "links": {
      "website": "https://stellar.org/",
      "whitepaper": "https://docs.google.com/viewerng/viewer?url=https://cdn.sanity.io/files/e2r40yh6/production-i18n/39856a57fa0c6e7d646b7db88f48f17688693fe4.pdf?dl=Stellar%20Consensus%20Protocol",
      "twitter": "https://twitter.com/StellarOrg",
      "reddit": "https://reddit.com/r/stellar",
      "telegram": null,
      "discord": "https://discord.com/invite/zVYdY3ktTn",
      "medium": "https://medium.com/stellar-community",
      "instagram": null,
      "tiktok": null,
      "youtube": null,
      "linkedin": "https://www.linkedin.com/company/stellar-development-foundation/",
      "twitch": null,
      "spotify": null,
      "naver": null,
      "wechat": null,
      "soundcloud": null
    },
    "code": "XLM",
    "rate": 0.49392732710334813,
    "volume": 1521508346,
    "cap": 14876328037,
    "delta": {
      "hour": 1.0319,
      "day": 0.9672,
      "week": 1.0171,
      "month": 5.4112,
      "quarter": 5.4914,
      "year": 4.0518
    }
  },
  {
    "name": "Wrapped Bitcoin",
    "rank": 17,
    "age": 2134,
    "color": "#f09444",
    "png32": "https://lcw.nyc3.cdn.digitaloceanspaces.com/production/currencies/32/wbtc.png",
    "png64": "https://lcw.nyc3.cdn.digitaloceanspaces.com/production/currencies/64/wbtc.png",
    "webp32": "https://lcw.nyc3.cdn.digitaloceanspaces.com/production/currencies/32/wbtc.webp",
    "webp64": "https://lcw.nyc3.cdn.digitaloceanspaces.com/production/currencies/64/wbtc.webp",
    "exchanges": 106,
    "markets": 325,
    "pairs": 113,
    "categories": [
      "wrapped_tokens",
      "asset_backed_tokens"
    ],
    "allTimeHighUSD": 102492.92628063427,
    "circulatingSupply": 137809,
    "totalSupply": 137809,
    "maxSupply": null,
    "links": {
      "website": "https://wbtc.network/",
      "whitepaper": "https://wbtc.network/assets/wrapped-tokens-whitepaper.pdf",
      "twitter": "https://x.com/WrappedBTC",
      "reddit": null,
      "telegram": null,
      "discord": null,
      "medium": null,
      "instagram": null,
      "tiktok": null,
      "youtube": null,
      "linkedin": null,
      "twitch": null,
      "spotify": null,
      "naver": null,
      "wechat": null,
      "soundcloud": null
    },
    "code": "WBTC",
    "rate": 101883.38372670126,
    "volume": 305290654,
    "cap": 14040447227,
    "delta": {
      "hour": 1.0372,
      "day": 1.0649,
      "week": 1.0683,
      "month": 1.4988,
      "quarter": 1.7999,
      "year": 2.3251
    }
  },
  {
    "name": "Bitcoin Cash",
    "rank": 18,
    "age": 2691,
    "color": "#f1f9f7",
    "png32": "https://lcw.nyc3.cdn.digitaloceanspaces.com/production/currencies/32/bch.png",
    "png64": "https://lcw.nyc3.cdn.digitaloceanspaces.com/production/currencies/64/bch.png",
    "webp32": "https://lcw.nyc3.cdn.digitaloceanspaces.com/production/currencies/32/bch.webp",
    "webp64": "https://lcw.nyc3.cdn.digitaloceanspaces.com/production/currencies/64/bch.webp",
    "exchanges": 95,
    "markets": 170,
    "pairs": 32,
    "categories": [
      "smart_contract_platforms"
    ],
    "allTimeHighUSD": 4355.62,
    "circulatingSupply": 19797578,
    "totalSupply": 19797578,
    "maxSupply": 21000000,
    "links": {
      "website": "https://bitcoincash.org/",
      "whitepaper": "https://www.bitcoincash.org/bitcoin.pdf",
      "twitter": null,
      "reddit": "https://reddit.com/r/Bitcoincash",
      "telegram": null,
      "discord": null,
      "medium": null,
      "instagram": null,
      "tiktok": null,
      "youtube": null,
      "linkedin": null,
      "twitch": null,
      "spotify": null,
      "naver": null,
      "wechat": null,
      "soundcloud": null
    },
    "code": "BCH",
    "rate": 596.4819244805742,
    "volume": 1017440833,
    "cap": 11808897425,
    "delta": {
      "hour": 1.0596,
      "day": 1.0496,
      "week": 1.1704,
      "month": 1.8124,
      "quarter": 1.936,
      "year": 2.3968
    }
  },
  {
    "name": "Sui",
    "rank": 19,
    "age": 601,
    "color": "#73bbe4",
    "png32": "https://lcw.nyc3.cdn.digitaloceanspaces.com/production/currencies/32/_sui.png",
    "png64": "https://lcw.nyc3.cdn.digitaloceanspaces.com/production/currencies/64/_sui.png",
    "webp32": "https://lcw.nyc3.cdn.digitaloceanspaces.com/production/currencies/32/_sui.webp",
    "webp64": "https://lcw.nyc3.cdn.digitaloceanspaces.com/production/currencies/64/_sui.webp",
    "exchanges": 64,
    "markets": 162,
    "pairs": 51,
    "categories": [
      "smart_contract_platforms"
    ],
    "allTimeHighUSD": 3.9833060354291354,
    "circulatingSupply": 2927660018,
    "totalSupply": 10000000000,
    "maxSupply": 10000000000,
    "links": {
      "website": "https://sui.io/",
      "whitepaper": "https://docs.sui.io/",
      "twitter": "https://twitter.com/mysten_labs",
      "reddit": null,
      "telegram": null,
      "discord": "https://discord.com/invite/sui",
      "medium": "https://medium.com/mysten-labs",
      "instagram": null,
      "tiktok": null,
      "youtube": null,
      "linkedin": "https://www.linkedin.com/company/mysten-labs",
      "twitch": null,
      "spotify": null,
      "naver": null,
      "wechat": null,
      "soundcloud": null
    },
    "code": "_SUI",
    "rate": 3.982973551231856,
    "volume": 2187746549,
    "cap": 11660792418,
    "delta": {
      "hour": 1.1002,
      "day": 1.0994,
      "week": 1.1379,
      "month": 2.1368,
      "quarter": 4.7987,
      "year": 6.207
    }
  },
  {
    "name": "Hedera Hashgraph",
    "rank": 20,
    "age": 1892,
    "color": "#f8f8f8",
    "png32": "https://lcw.nyc3.cdn.digitaloceanspaces.com/production/currencies/32/hbar.png",
    "png64": "https://lcw.nyc3.cdn.digitaloceanspaces.com/production/currencies/64/hbar.png",
    "webp32": "https://lcw.nyc3.cdn.digitaloceanspaces.com/production/currencies/32/hbar.webp",
    "webp64": "https://lcw.nyc3.cdn.digitaloceanspaces.com/production/currencies/64/hbar.webp",
    "exchanges": 40,
    "markets": 76,
    "pairs": 35,
    "categories": [
      "smart_contract_platforms"
    ],
    "allTimeHighUSD": 0.569398985191319,
    "circulatingSupply": 38198864521,
    "totalSupply": 50000000000,
    "maxSupply": 50000000000,
    "links": {
      "website": "https://hedera.com/",
      "whitepaper": "https://hedera.com/papers",
      "twitter": "https://twitter.com/hedera",
      "reddit": "https://reddit.com/r/hashgraph",
      "telegram": "https://t.me/hederahashgraph",
      "discord": "https://discord.com/invite/hedera",
      "medium": "https://medium.com/hedera",
      "instagram": "https://www.instagram.com/hashgraph/",
      "tiktok": null,
      "youtube": "https://www.youtube.com/hederahashgraph",
      "linkedin": "https://www.linkedin.com/company/hashgraph/",
      "twitch": null,
      "spotify": null,
      "naver": null,
      "wechat": null,
      "soundcloud": null
    },
    "code": "HBAR",
    "rate": 0.30026084293920585,
    "volume": 2627497013,
    "cap": 11469623260,
    "delta": {
      "hour": 0.989,
      "day": 0.914,
      "week": 2.1613,
      "month": 6.9551,
      "quarter": 6.2196,
      "year": 4.3236
    }
  },
  {
    "name": "OKB",
    "rank": 21,
    "age": 2044,
    "color": "#050505",
    "png32": "https://lcw.nyc3.cdn.digitaloceanspaces.com/production/currencies/32/okb.png",
    "png64": "https://lcw.nyc3.cdn.digitaloceanspaces.com/production/currencies/64/okb.png",
    "webp32": "https://lcw.nyc3.cdn.digitaloceanspaces.com/production/currencies/32/okb.webp",
    "webp64": "https://lcw.nyc3.cdn.digitaloceanspaces.com/production/currencies/64/okb.webp",
    "exchanges": 19,
    "markets": 23,
    "pairs": 5,
    "categories": [
      "cex"
    ],
    "allTimeHighUSD": 73.9085570691034,
    "circulatingSupply": 178341898,
    "totalSupply": 178341898,
    "maxSupply": 300000000,
    "links": {
      "website": "https://www.okx.com/",
      "whitepaper": "https://okexchain-docs.readthedocs.io/en/latest/",
      "twitter": "https://twitter.com/okx",
      "reddit": "https://reddit.com/r/OKX",
      "telegram": "https://t.me/OKXOfficial_English",
      "discord": "https://discord.com/invite/2rynEUqJxP",
      "medium": "https://medium.com/okex-blog",
      "instagram": "https://www.instagram.com/okx_official/",
      "tiktok": "https://www.tiktok.com/@okx",
      "youtube": "https://www.youtube.com/@OKXCryptoExchange",
      "linkedin": "https://www.linkedin.com/company/okxofficial/",
      "twitch": null,
      "spotify": null,
      "naver": null,
      "wechat": null,
      "soundcloud": null
    },
    "code": "OKB",
    "rate": 57.55735658180724,
    "volume": 39929775,
    "cap": 10264888216,
    "delta": {
      "hour": 1.0248,
      "day": 0.9405,
      "week": 1.0559,
      "month": 1.5419,
      "quarter": 1.5685,
      "year": 0.998
    }
  },
  {
    "name": "Litecoin",
    "rank": 22,
    "age": 4236,
    "color": "#345c9c",
    "png32": "https://lcw.nyc3.cdn.digitaloceanspaces.com/production/currencies/32/ltc.png",
    "png64": "https://lcw.nyc3.cdn.digitaloceanspaces.com/production/currencies/64/ltc.png",
    "webp32": "https://lcw.nyc3.cdn.digitaloceanspaces.com/production/currencies/32/ltc.webp",
    "webp64": "https://lcw.nyc3.cdn.digitaloceanspaces.com/production/currencies/64/ltc.webp",
    "exchanges": 143,
    "markets": 347,
    "pairs": 99,
    "categories": [
      "privacy_coins"
    ],
    "allTimeHighUSD": 413.084055609638,
    "circulatingSupply": 75269205,
    "totalSupply": 75269205,
    "maxSupply": 84000000,
    "links": {
      "website": "https://litecoin.org/",
      "whitepaper": "https://litecoin.info/docs",
      "twitter": "https://twitter.com/litecoin",
      "reddit": "https://reddit.com/r/litecoin",
      "telegram": "https://t.me/litecoin",
      "discord": null,
      "medium": null,
      "instagram": "https://instagram.com/litecoindotcom",
      "tiktok": null,
      "youtube": null,
      "linkedin": null,
      "twitch": null,
      "spotify": null,
      "naver": null,
      "wechat": null,
      "soundcloud": null
    },
    "code": "LTC",
    "rate": 130.3484504771626,
    "volume": 3077423398,
    "cap": 9811224240,
    "delta": {
      "hour": 1.02,
      "day": 1.0044,
      "week": 1.3338,
      "month": 1.9722,
      "quarter": 1.9605,
      "year": 1.7761
    }
  },
  {
    "name": "NEAR Protocol",
    "rank": 23,
    "age": 1502,
    "color": "#040404",
    "png32": "https://lcw.nyc3.cdn.digitaloceanspaces.com/production/currencies/32/near.png",
    "png64": "https://lcw.nyc3.cdn.digitaloceanspaces.com/production/currencies/64/near.png",
    "webp32": "https://lcw.nyc3.cdn.digitaloceanspaces.com/production/currencies/32/near.webp",
    "webp64": "https://lcw.nyc3.cdn.digitaloceanspaces.com/production/currencies/64/near.webp",
    "exchanges": 83,
    "markets": 146,
    "pairs": 43,
    "categories": [
      "smart_contract_platforms"
    ],
    "allTimeHighUSD": 20.46907836312353,
    "circulatingSupply": 1217906154,
    "totalSupply": 1223574730,
    "maxSupply": null,
    "links": {
      "website": "https://near.org/",
      "whitepaper": "https://docs.near.org/",
      "twitter": "https://twitter.com/nearprotocol",
      "reddit": "https://reddit.com/r/nearprotocol",
      "telegram": "https://t.me/cryptonear",
      "discord": "https://discord.com/invite/zfhfRpaM4m",
      "medium": "https://medium.com/nearprotocol",
      "instagram": "https://www.instagram.com/near_protocol",
      "tiktok": null,
      "youtube": "https://www.youtube.com/@NEARProtocol",
      "linkedin": null,
      "twitch": null,
      "spotify": null,
      "naver": null,
      "wechat": "https://pages.near.org/ecosystem/community/wechat/",
      "soundcloud": null
    },
    "code": "NEAR",
    "rate": 7.441601555184537,
    "volume": 1196054003,
    "cap": 9063172329,
    "delta": {
      "hour": 1.0327,
      "day": 1.0233,
      "week": 1.1102,
      "month": 2.0399,
      "quarter": 1.9819,
      "year": 3.1763
    }
  },
  {
    "name": "Pepe",
    "rank": 24,
    "age": 597,
    "color": "#488c40",
    "png32": "https://lcw.nyc3.cdn.digitaloceanspaces.com/production/currencies/32/____pepe.png",
    "png64": "https://lcw.nyc3.cdn.digitaloceanspaces.com/production/currencies/64/____pepe.png",
    "webp32": "https://lcw.nyc3.cdn.digitaloceanspaces.com/production/currencies/32/____pepe.webp",
    "webp64": "https://lcw.nyc3.cdn.digitaloceanspaces.com/production/currencies/64/____pepe.webp",
    "exchanges": 60,
    "markets": 77,
    "pairs": 17,
    "categories": [
      "meme"
    ],
    "allTimeHighUSD": 0.000025045977194285988,
    "circulatingSupply": 413738229656936,
    "totalSupply": 413772823122434,
    "maxSupply": 420690000000000,
    "links": {
      "website": "https://www.pepe.vip/",
      "whitepaper": null,
      "twitter": "https://twitter.com/pepecoineth",
      "reddit": null,
      "telegram": "https://t.me/pepecoineth",
      "discord": null,
      "medium": null,
      "instagram": null,
      "tiktok": null,
      "youtube": null,
      "linkedin": null,
      "twitch": null,
      "spotify": null,
      "naver": null,
      "wechat": null,
      "soundcloud": null
    },
    "code": "____PEPE",
    "rate": 0.000021182794381328836,
    "volume": 2667121888,
    "cap": 8764131846,
    "delta": {
      "hour": 1.0211,
      "day": 1.0288,
      "week": 1.0732,
      "month": 2.6229,
      "quarter": 2.9529,
      "year": 13.5484
    }
  },
  {
    "name": "Polygon Ecosystem Token",
    "rank": 25,
    "age": 406,
    "color": "#3edfda",
    "png32": "https://lcw.nyc3.cdn.digitaloceanspaces.com/production/currencies/32/pol.png",
    "png64": "https://lcw.nyc3.cdn.digitaloceanspaces.com/production/currencies/64/pol.png",
    "webp32": "https://lcw.nyc3.cdn.digitaloceanspaces.com/production/currencies/32/pol.webp",
    "webp64": "https://lcw.nyc3.cdn.digitaloceanspaces.com/production/currencies/64/pol.webp",
    "exchanges": 112,
    "markets": 860,
    "pairs": 434,
    "categories": [
      "smart_contract_platforms",
      "governance"
    ],
    "allTimeHighUSD": 1.28668374279728,
    "circulatingSupply": 11953043813.2308,
    "totalSupply": 20469142198.8836,
    "maxSupply": null,
    "links": {
      "website": "https://polygon.technology/",
      "whitepaper": "https://polygon.technology/papers/pol-whitepaper",
      "twitter": "https://x.com/0xPolygonLabs",
      "reddit": "https://reddit.com/r/0xPolygon",
      "telegram": "https://t.me/polygonofficial",
      "discord": "https://discord.com/invite/0xPolygon",
      "medium": null,
      "instagram": "https://www.instagram.com/0xpolygon/",
      "tiktok": null,
      "youtube": "https://www.youtube.com/@0xPolygonTV",
      "linkedin": "https://www.linkedin.com/company/polygonlabs/",
      "twitch": null,
      "spotify": null,
      "naver": null,
      "wechat": null,
      "soundcloud": null
    },
    "code": "POL",
    "rate": 0.698878443741373,
    "volume": 1105230778,
    "cap": 8353724658,
    "delta": {
      "hour": 1.0184,
      "day": 0.9769,
      "week": 1.2466,
      "month": 2.3699,
      "quarter": 1.8847,
      "year": 0.8589
    }
  },
  {
    "name": "Uniswap",
    "rank": 26,
    "age": 1539,
    "color": "#fceaf3",
    "png32": "https://lcw.nyc3.cdn.digitaloceanspaces.com/production/currencies/32/uni.png",
    "png64": "https://lcw.nyc3.cdn.digitaloceanspaces.com/production/currencies/64/uni.png",
    "webp32": "https://lcw.nyc3.cdn.digitaloceanspaces.com/production/currencies/32/uni.webp",
    "webp64": "https://lcw.nyc3.cdn.digitaloceanspaces.com/production/currencies/64/uni.webp",
    "exchanges": 118,
    "markets": 239,
    "pairs": 62,
    "categories": [
      "dex",
      "yield_farming",
      "governance"
    ],
    "allTimeHighUSD": 45.009351908031135,
    "circulatingSupply": 529362926,
    "totalSupply": 1000000000,
    "maxSupply": 1000000000,
    "links": {
      "website": "https://app.uniswap.org/",
      "whitepaper": "https://uniswap.org/whitepaper-v3.pdf",
      "twitter": "https://twitter.com/Uniswap",
      "reddit": "https://reddit.com/r/Uniswap",
      "telegram": null,
      "discord": "https://discord.com/invite/FCfyBSbCU5",
      "medium": null,
      "instagram": null,
      "tiktok": null,
      "youtube": null,
      "linkedin": null,
      "twitch": null,
      "spotify": null,
      "naver": null,
      "wechat": null,
      "soundcloud": null
    },
    "code": "UNI",
    "rate": 15.259048083838596,
    "volume": 1322556996,
    "cap": 8077574341,
    "delta": {
      "hour": 1.0134,
      "day": 1.0275,
      "week": 1.2139,
      "month": 2.2258,
      "quarter": 2.4195,
      "year": 2.4624
    }
  },
  {
    "name": "Arbitrum",
    "rank": 27,
    "age": 622,
    "color": "#dbe9f3",
    "png32": "https://lcw.nyc3.cdn.digitaloceanspaces.com/production/currencies/32/arb.png",
    "png64": "https://lcw.nyc3.cdn.digitaloceanspaces.com/production/currencies/64/arb.png",
    "webp32": "https://lcw.nyc3.cdn.digitaloceanspaces.com/production/currencies/32/arb.webp",
    "webp64": "https://lcw.nyc3.cdn.digitaloceanspaces.com/production/currencies/64/arb.webp",
    "exchanges": 96,
    "markets": 203,
    "pairs": 51,
    "categories": [
      "governance"
    ],
    "allTimeHighUSD": 11.6446,
    "circulatingSupply": 6624303618,
    "totalSupply": 9999998977,
    "maxSupply": null,
    "links": {
      "website": "https://arbitrum.foundation",
      "whitepaper": "https://docs.arbitrum.foundation/",
      "twitter": "https://twitter.com/arbitrum",
      "reddit": null,
      "telegram": null,
      "discord": "https://discord.com/invite/arbitrum",
      "medium": " https://medium.com/offchainlabs",
      "instagram": null,
      "tiktok": null,
      "youtube": null,
      "linkedin": null,
      "twitch": null,
      "spotify": null,
      "naver": null,
      "wechat": null,
      "soundcloud": null
    },
    "code": "ARB",
    "rate": 1.1170475017928836,
    "volume": 1395024205,
    "cap": 7399661807,
    "delta": {
      "hour": 1.015,
      "day": 1.0391,
      "week": 1.1988,
      "month": 2.3376,
      "quarter": 2.2266,
      "year": 1.0231
    }
  },
  {
    "name": "Aptos",
    "rank": 28,
    "age": 778,
    "color": "#040404",
    "png32": "https://lcw.nyc3.cdn.digitaloceanspaces.com/production/currencies/32/apt.png",
    "png64": "https://lcw.nyc3.cdn.digitaloceanspaces.com/production/currencies/64/apt.png",
    "webp32": "https://lcw.nyc3.cdn.digitaloceanspaces.com/production/currencies/32/apt.webp",
    "webp64": "https://lcw.nyc3.cdn.digitaloceanspaces.com/production/currencies/64/apt.webp",
    "exchanges": 40,
    "markets": 61,
    "pairs": 11,
    "categories": [
      "smart_contract_platforms",
      "nfts"
    ],
    "allTimeHighUSD": 20.24643258298312,
    "circulatingSupply": 535220531,
    "totalSupply": 1129242261,
    "maxSupply": null,
    "links": {
      "website": "https://aptosfoundation.org/",
      "whitepaper": "https://aptos.dev/aptos-white-paper/",
      "twitter": "https://twitter.com/AptosFoundation",
      "reddit": null,
      "telegram": "https://t.me/AptosTG",
      "discord": "https://discord.com/invite/aptoslabs",
      "medium": "https://aptoslabs.medium.com/",
      "instagram": null,
      "tiktok": null,
      "youtube": null,
      "linkedin": "https://www.linkedin.com/company/aptoslabs/a",
      "twitch": null,
      "spotify": null,
      "naver": null,
      "wechat": null,
      "soundcloud": null
    },
    "code": "APT",
    "rate": 13.6836911896246,
    "volume": 595722311,
    "cap": 7323792464,
    "delta": {
      "hour": 1.0197,
      "day": 0.9603,
      "week": 1.0672,
      "month": 1.6781,
      "quarter": 2.3431,
      "year": 1.7853
    }
  },
  {
    "name": "Internet Computer",
    "rank": 29,
    "age": 1303,
    "color": "#ea594e",
    "png32": "https://lcw.nyc3.cdn.digitaloceanspaces.com/production/currencies/32/icp.png",
    "png64": "https://lcw.nyc3.cdn.digitaloceanspaces.com/production/currencies/64/icp.png",
    "webp32": "https://lcw.nyc3.cdn.digitaloceanspaces.com/production/currencies/32/icp.webp",
    "webp64": "https://lcw.nyc3.cdn.digitaloceanspaces.com/production/currencies/64/icp.webp",
    "exchanges": 45,
    "markets": 79,
    "pairs": 25,
    "categories": [
      "smart_contract_platforms",
      "cloud_hosting",
      "storage",
      "governance"
    ],
    "allTimeHighUSD": 494.5636424153892,
    "circulatingSupply": 462717821,
    "totalSupply": 517739778,
    "maxSupply": null,
    "links": {
      "website": "https://internetcomputer.org/",
      "whitepaper": "https://internetcomputer.org/whitepaper.pdf",
      "twitter": "https://twitter.com/dfinity",
      "reddit": "https://reddit.com/r/dfinity",
      "telegram": "https://t.me/dfinity/",
      "discord": "https://discord.com/invite/cE92CymEmJ",
      "medium": "https://medium.com/dfinity-network-blog",
      "instagram": null,
      "tiktok": null,
      "youtube": null,
      "linkedin": null,
      "twitch": null,
      "spotify": null,
      "naver": null,
      "wechat": null,
      "soundcloud": null
    },
    "code": "ICP",
    "rate": 14.309221027460628,
    "volume": 494178449,
    "cap": 6621131574,
    "delta": {
      "hour": 1.0128,
      "day": 0.9963,
      "week": 1.2633,
      "month": 2.0227,
      "quarter": 1.9616,
      "year": 2.8045
    }
  },
  {
    "name": "VeChain",
    "rank": 30,
    "age": 2661,
    "color": "#6488e1",
    "png32": "https://lcw.nyc3.cdn.digitaloceanspaces.com/production/currencies/32/vet.png",
    "png64": "https://lcw.nyc3.cdn.digitaloceanspaces.com/production/currencies/64/vet.png",
    "webp32": "https://lcw.nyc3.cdn.digitaloceanspaces.com/production/currencies/32/vet.webp",
    "webp64": "https://lcw.nyc3.cdn.digitaloceanspaces.com/production/currencies/64/vet.webp",
    "exchanges": 43,
    "markets": 84,
    "pairs": 27,
    "categories": [
      "logistics",
      "ai",
      "iot",
      "smart_contract_platforms"
    ],
    "allTimeHighUSD": 0.26773718608293,
    "circulatingSupply": 80985041177,
    "totalSupply": 85985041177,
    "maxSupply": 86712634466,
    "links": {
      "website": "https://vechain.org/",
      "whitepaper": "https://www.vechain.org/assets/whitepaper/whitepaper-3-0.pdf",
      "twitter": "https://twitter.com/vechainofficial",
      "reddit": "https://reddit.com/r/vechain",
      "telegram": "https://t.me/vechainandfriends",
      "discord": "https://discord.com/invite/vechain",
      "medium": "https://vechainofficial.medium.com/",
      "instagram": "https://www.instagram.com/vechainfoundation_official/",
      "tiktok": null,
      "youtube": "https://www.youtube.com/@vechainofficial",
      "linkedin": "https://www.linkedin.com/company/vechain-foundation/",
      "twitch": null,
      "spotify": null,
      "naver": null,
      "wechat": null,
      "soundcloud": null
    },
    "code": "VET",
    "rate": 0.06965698695916386,
    "volume": 622786171,
    "cap": 5641173957,
    "delta": {
      "hour": 1.0047,
      "day": 0.973,
      "week": 1.6568,
      "month": 3.5933,
      "quarter": 3.3549,
      "year": 2.8256
    }
  },
  {
    "name": "Ethereum Classic",
    "rank": 31,
    "age": 3055,
    "color": "#3ab93a",
    "png32": "https://lcw.nyc3.cdn.digitaloceanspaces.com/production/currencies/32/etc.png",
    "png64": "https://lcw.nyc3.cdn.digitaloceanspaces.com/production/currencies/64/etc.png",
    "webp32": "https://lcw.nyc3.cdn.digitaloceanspaces.com/production/currencies/32/etc.webp",
    "webp64": "https://lcw.nyc3.cdn.digitaloceanspaces.com/production/currencies/64/etc.webp",
    "exchanges": 75,
    "markets": 134,
    "pairs": 23,
    "categories": [
      "smart_contract_platforms"
    ],
    "allTimeHighUSD": 168.98136358110946,
    "circulatingSupply": 149815426,
    "totalSupply": 210700000,
    "maxSupply": 210700000,
    "links": {
      "website": "https://ethereumclassic.org/",
      "whitepaper": "https://github.com/ethereum/wiki/wiki/White-Paper",
      "twitter": "https://twitter.com/eth_classic",
      "reddit": "https://reddit.com/r/EthereumClassic",
      "telegram": null,
      "discord": "https://discord.com/invite/bMGuZsA",
      "medium": null,
      "instagram": null,
      "tiktok": null,
      "youtube": null,
      "linkedin": null,
      "twitch": null,
      "spotify": null,
      "naver": null,
      "wechat": null,
      "soundcloud": null
    },
    "code": "ETC",
    "rate": 36.8608801591695,
    "volume": 907723521,
    "cap": 5522328463,
    "delta": {
      "hour": 1.016,
      "day": 1.0286,
      "week": 1.1648,
      "month": 2.0726,
      "quarter": 2.0813,
      "year": 1.8328
    }
  },
  {
    "name": "Dai",
    "rank": 32,
    "age": 2535,
    "color": "#fcb934",
    "png32": "https://lcw.nyc3.cdn.digitaloceanspaces.com/production/currencies/32/dai.png",
    "png64": "https://lcw.nyc3.cdn.digitaloceanspaces.com/production/currencies/64/dai.png",
    "webp32": "https://lcw.nyc3.cdn.digitaloceanspaces.com/production/currencies/32/dai.webp",
    "webp64": "https://lcw.nyc3.cdn.digitaloceanspaces.com/production/currencies/64/dai.webp",
    "exchanges": 122,
    "markets": 468,
    "pairs": 193,
    "categories": [
      "stablecoins"
    ],
    "allTimeHighUSD": 1.1508565406794649,
    "circulatingSupply": 5443293194.297144,
    "totalSupply": 3558048518,
    "maxSupply": null,
    "links": {
      "website": "https://makerdao.com/",
      "whitepaper": "https://makerdao.com/en/whitepaper/#the-dai-stablecoin",
      "twitter": "https://x.com/makerDAO",
      "reddit": "https://reddit.com/r/makerDAO",
      "telegram": "https://t.me/makerdaoOfficial",
      "discord": null,
      "medium": null,
      "instagram": null,
      "tiktok": null,
      "youtube": "https://www.youtube.com/@MakerDAO",
      "linkedin": null,
      "twitch": null,
      "spotify": null,
      "naver": null,
      "wechat": null,
      "soundcloud": null
    },
    "code": "DAI",
    "rate": 0.9977518223611811,
    "volume": 199060516,
    "cap": 5431055704,
    "delta": {
      "hour": 0.9982,
      "day": 0.998,
      "week": 0.9999,
      "month": 0.9974,
      "quarter": 0.9993,
      "year": 0.9967
    }
  },
  {
    "name": "Cronos",
    "rank": 33,
    "age": 2093,
    "color": "#0c2c6c",
    "png32": "https://lcw.nyc3.cdn.digitaloceanspaces.com/production/currencies/32/cro.png",
    "png64": "https://lcw.nyc3.cdn.digitaloceanspaces.com/production/currencies/64/cro.png",
    "webp32": "https://lcw.nyc3.cdn.digitaloceanspaces.com/production/currencies/32/cro.webp",
    "webp64": "https://lcw.nyc3.cdn.digitaloceanspaces.com/production/currencies/64/cro.webp",
    "exchanges": 27,
    "markets": 95,
    "pairs": 65,
    "categories": [
      "cex",
      "smart_contract_platforms",
      "debit_cards",
      "wallets"
    ],
    "allTimeHighUSD": 0.9516849148075289,
    "circulatingSupply": 25263013692,
    "totalSupply": 30263013692,
    "maxSupply": null,
    "links": {
      "website": "https://crypto.com/",
      "whitepaper": "https://whitepaper.cronos.org/",
      "twitter": "https://x.com/cryptocom",
      "reddit": "https://reddit.com/r/Crypto_com",
      "telegram": "https://t.me/CryptoComOfficial",
      "discord": "https://discord.com/invite/nsp9JTC",
      "medium": "https://medium.com/@crypto.com",
      "instagram": "https://instagram.com/cryptocomofficial",
      "tiktok": null,
      "youtube": "https://www.youtube.com/@CryptoComOfficial",
      "linkedin": null,
      "twitch": null,
      "spotify": null,
      "naver": null,
      "wechat": null,
      "soundcloud": null
    },
    "code": "CRO",
    "rate": 0.20998916189141273,
    "volume": 173843142,
    "cap": 5304959072,
    "delta": {
      "hour": 1.0167,
      "day": 1.0582,
      "week": 1.1913,
      "month": 2.9589,
      "quarter": 2.6902,
      "year": 2.1904
    }
  },
  {
    "name": "Render Token",
    "rank": 34,
    "age": 1629,
    "color": "#cc1113",
    "png32": "https://lcw.nyc3.cdn.digitaloceanspaces.com/production/currencies/32/render.png",
    "png64": "https://lcw.nyc3.cdn.digitaloceanspaces.com/production/currencies/64/render.png",
    "webp32": "https://lcw.nyc3.cdn.digitaloceanspaces.com/production/currencies/32/render.webp",
    "webp64": "https://lcw.nyc3.cdn.digitaloceanspaces.com/production/currencies/64/render.webp",
    "exchanges": 80,
    "markets": 133,
    "pairs": 39,
    "categories": [
      "cloud_hosting"
    ],
    "allTimeHighUSD": 13.630067683987447,
    "circulatingSupply": 516273134,
    "totalSupply": 532450926,
    "maxSupply": 644245094,
    "links": {
      "website": "https://rendernetwork.com/",
      "whitepaper": "https://docs.google.com/viewerng/viewer?url=https://framerusercontent.com/assets/rIeLSxNt8ws08bPfc1Mp034Cko.pdf",
      "twitter": "https://x.com/rendernetwork",
      "reddit": "https://reddit.com/r/RenderNetwork/",
      "telegram": "https://t.me/rendernetwork",
      "discord": "https://discord.com/invite/rendernetwork",
      "medium": "https://rendernetwork.medium.com/",
      "instagram": null,
      "tiktok": null,
      "youtube": "https://www.youtube.com/@RenderNetwork",
      "linkedin": null,
      "twitch": null,
      "spotify": null,
      "naver": null,
      "wechat": null,
      "soundcloud": null
    },
    "code": "RENDER",
    "rate": 10.207502579792953,
    "volume": 2130161448,
    "cap": 5269859347,
    "delta": {
      "hour": 1.2215,
      "day": 1.1577,
      "week": 1.2552,
      "month": 2.3808,
      "quarter": 2.1428,
      "year": 2.7501
    }
  },
  {
    "name": "bittensor",
    "rank": 35,
    "age": 638,
    "color": "#040404",
    "png32": "https://lcw.nyc3.cdn.digitaloceanspaces.com/production/currencies/32/____tao.png",
    "png64": "https://lcw.nyc3.cdn.digitaloceanspaces.com/production/currencies/64/____tao.png",
    "webp32": "https://lcw.nyc3.cdn.digitaloceanspaces.com/production/currencies/32/____tao.webp",
    "webp64": "https://lcw.nyc3.cdn.digitaloceanspaces.com/production/currencies/64/____tao.webp",
    "exchanges": 14,
    "markets": 17,
    "pairs": 6,
    "categories": [
      "ai"
    ],
    "allTimeHighUSD": 777.3326187345224,
    "circulatingSupply": 7849306,
    "totalSupply": 7849306,
    "maxSupply": 21000000,
    "links": {
      "website": "https://bittensor.com/",
      "whitepaper": "https://docs.bittensor.com/",
      "twitter": "https://twitter.com/bittensor_",
      "reddit": "https://reddit.com/r/bittensor_",
      "telegram": "https://t.me/bittensor",
      "discord": "https://discord.com/invite/bittensor",
      "medium": "https://bittensor.medium.com/",
      "instagram": null,
      "tiktok": null,
      "youtube": "https://www.youtube.com/@Bittensor",
      "linkedin": null,
      "twitch": null,
      "spotify": null,
      "naver": null,
      "wechat": null,
      "soundcloud": null
    },
    "code": "____TAO",
    "rate": 666.8123994640821,
    "volume": 378589865,
    "cap": 5234014567,
    "delta": {
      "hour": 1.0339,
      "day": 1.0653,
      "week": 1.1917,
      "month": 1.5841,
      "quarter": 2.7607,
      "year": 1.9362
    }
  },
  {
    "name": "Artificial Superintelligence Alliance",
    "rank": 36,
    "age": 2102,
    "color": "#1e2b44",
    "png32": "https://lcw.nyc3.cdn.digitaloceanspaces.com/production/currencies/32/fet.png",
    "png64": "https://lcw.nyc3.cdn.digitaloceanspaces.com/production/currencies/64/fet.png",
    "webp32": "https://lcw.nyc3.cdn.digitaloceanspaces.com/production/currencies/32/fet.webp",
    "webp64": "https://lcw.nyc3.cdn.digitaloceanspaces.com/production/currencies/64/fet.webp",
    "exchanges": 47,
    "markets": 67,
    "pairs": 16,
    "categories": [
      "ai"
    ],
    "allTimeHighUSD": 3.4731180781797693,
    "circulatingSupply": 2641543962,
    "totalSupply": 2719493896,
    "maxSupply": null,
    "links": {
      "website": "https://fetch.ai/",
      "whitepaper": "https://docs.fetch.ai/",
      "twitter": "https://x.com/fetch_ai",
      "reddit": "https://reddit.com/r/FetchAI_Community",
      "telegram": "https://t.me/fetch_ai",
      "discord": "https://discord.com/invite/yypdAsRPYm",
      "medium": "https://medium.com/fetch-ai",
      "instagram": null,
      "tiktok": null,
      "youtube": "https://www.youtube.com/@fetchai",
      "linkedin": "https://www.linkedin.com/company/fetch-ai/",
      "twitch": null,
      "spotify": null,
      "naver": null,
      "wechat": null,
      "soundcloud": null
    },
    "code": "FET",
    "rate": 1.8409951596922174,
    "volume": 712638544,
    "cap": 4863069648,
    "delta": {
      "hour": 1.0204,
      "day": 0.9646,
      "week": 1.2518,
      "month": 1.6233,
      "quarter": 1.6938,
      "year": 3.4913
    }
  },
  {
    "name": "Filecoin",
    "rank": 37,
    "age": 1511,
    "color": "#0492fc",
    "png32": "https://lcw.nyc3.cdn.digitaloceanspaces.com/production/currencies/32/fil.png",
    "png64": "https://lcw.nyc3.cdn.digitaloceanspaces.com/production/currencies/64/fil.png",
    "webp32": "https://lcw.nyc3.cdn.digitaloceanspaces.com/production/currencies/32/fil.webp",
    "webp64": "https://lcw.nyc3.cdn.digitaloceanspaces.com/production/currencies/64/fil.webp",
    "exchanges": 53,
    "markets": 83,
    "pairs": 17,
    "categories": [
      "smart_contract_platforms",
      "storage",
      "cloud_hosting"
    ],
    "allTimeHighUSD": 237.64668979882163,
    "circulatingSupply": 607891086,
    "totalSupply": 1959880497.9314,
    "maxSupply": 2000000000,
    "links": {
      "website": "https://filecoin.io/",
      "whitepaper": "https://docs.filecoin.io/",
      "twitter": "https://x.com/Filecoin",
      "reddit": "https://reddit.com/r/filecoin",
      "telegram": "https://t.me/Filecoin",
      "discord": "https://discord.com/invite/yeQ2hcd2TD",
      "medium": null,
      "instagram": null,
      "tiktok": null,
      "youtube": "https://www.youtube.com/@FilecoinProject",
      "linkedin": null,
      "twitch": null,
      "spotify": null,
      "naver": null,
      "wechat": "https://weixin.qq.com/r/1xz54Y-EctINrcuC90nF",
      "soundcloud": null
    },
    "code": "FIL",
    "rate": 7.954967281870766,
    "volume": 1355385011,
    "cap": 4835753700,
    "delta": {
      "hour": 1.0191,
      "day": 1.0478,
      "week": 1.3942,
      "month": 2.4052,
      "quarter": 2.3423,
      "year": 1.6749
    }
  },
  {
    "name": "WhiteBIT Coin",
    "rank": 38,
    "age": 831,
    "color": "#f7df5c",
    "png32": "https://lcw.nyc3.cdn.digitaloceanspaces.com/production/currencies/32/wbt.png",
    "png64": "https://lcw.nyc3.cdn.digitaloceanspaces.com/production/currencies/64/wbt.png",
    "webp32": "https://lcw.nyc3.cdn.digitaloceanspaces.com/production/currencies/32/wbt.webp",
    "webp64": "https://lcw.nyc3.cdn.digitaloceanspaces.com/production/currencies/64/wbt.webp",
    "exchanges": 5,
    "markets": 6,
    "pairs": 2,
    "categories": [
      "cex",
      "smart_contract_platforms"
    ],
    "allTimeHighUSD": 24.90370416064677,
    "circulatingSupply": 192885858,
    "totalSupply": 365135594,
    "maxSupply": 400000000,
    "links": {
      "website": "https://whitebit.com/",
      "whitepaper": "https://cdn.whitechain.io/whitepaper-en.pdf",
      "twitter": "https://twitter.com/WhiteBit",
      "reddit": null,
      "telegram": "https://t.me/White_Bit",
      "discord": null,
      "medium": "https://medium.com/whitebit",
      "instagram": "https://www.instagram.com/whitebit/",
      "tiktok": null,
      "youtube": null,
      "linkedin": null,
      "twitch": null,
      "spotify": null,
      "naver": null,
      "wechat": null,
      "soundcloud": null
    },
    "code": "WBT",
    "rate": 23.465554264629763,
    "volume": 32394570,
    "cap": 4526173567,
    "delta": {
      "hour": 1.0006,
      "day": 1.0013,
      "week": 0.9923,
      "month": 1.2422,
      "quarter": 2.1752,
      "year": 4.1993
    }
  },
  {
    "name": "Stacks",
    "rank": 39,
    "age": 1800,
    "color": "#4c4cec",
    "png32": "https://lcw.nyc3.cdn.digitaloceanspaces.com/production/currencies/32/_stx.png",
    "png64": "https://lcw.nyc3.cdn.digitaloceanspaces.com/production/currencies/64/_stx.png",
    "webp32": "https://lcw.nyc3.cdn.digitaloceanspaces.com/production/currencies/32/_stx.webp",
    "webp64": "https://lcw.nyc3.cdn.digitaloceanspaces.com/production/currencies/64/_stx.webp",
    "exchanges": 28,
    "markets": 51,
    "pairs": 19,
    "categories": [
      "smart_contract_platforms",
      "dns"
    ],
    "allTimeHighUSD": 3.8428900303261804,
    "circulatingSupply": 1503423440,
    "totalSupply": 1503423440,
    "maxSupply": 1818000000,
    "links": {
      "website": "https://www.stacks.co/",
      "whitepaper": "https://docs.stacks.co/docs/intro",
      "twitter": "https://twitter.com/stacks",
      "reddit": "https://reddit.com/r/stacks",
      "telegram": "https://t.me/BlockstackChat",
      "discord": "https://discord.com/invite/zrvWsQC",
      "medium": null,
      "instagram": null,
      "tiktok": null,
      "youtube": "https://www.youtube.com/@Stacks-btc",
      "linkedin": null,
      "twitch": null,
      "spotify": null,
      "naver": null,
      "wechat": null,
      "soundcloud": null
    },
    "code": "_STX",
    "rate": 2.9337024705709274,
    "volume": 511506293,
    "cap": 4410597060,
    "delta": {
      "hour": 1.1372,
      "day": 1.1258,
      "week": 1.3016,
      "month": 1.9919,
      "quarter": 2.0984,
      "year": 2.5002
    }
  },
  {
    "name": "Algorand",
    "rank": 40,
    "age": 1993,
    "color": "#efefef",
    "png32": "https://lcw.nyc3.cdn.digitaloceanspaces.com/production/currencies/32/algo.png",
    "png64": "https://lcw.nyc3.cdn.digitaloceanspaces.com/production/currencies/64/algo.png",
    "webp32": "https://lcw.nyc3.cdn.digitaloceanspaces.com/production/currencies/32/algo.webp",
    "webp64": "https://lcw.nyc3.cdn.digitaloceanspaces.com/production/currencies/64/algo.webp",
    "exchanges": 46,
    "markets": 112,
    "pairs": 51,
    "categories": [
      "smart_contract_platforms"
    ],
    "allTimeHighUSD": 3.2281520514805,
    "circulatingSupply": 8298319637,
    "totalSupply": 10000000000,
    "maxSupply": 10000000000,
    "links": {
      "website": "https://algorand.co/",
      "whitepaper": "https://developer.algorand.org/docs/",
      "twitter": "https://twitter.com/AlgoFoundation",
      "reddit": "https://reddit.com/r/AlgorandOfficial",
      "telegram": "https://t.me/AlgorandFoundation",
      "discord": "https://discord.gg/84AActu3at",
      "medium": "https://medium.com/algorand",
      "instagram": null,
      "tiktok": null,
      "youtube": "https://www.youtube.com/@algorand",
      "linkedin": "https://www.linkedin.com/company/algorand/",
      "twitch": null,
      "spotify": null,
      "naver": null,
      "wechat": null,
      "soundcloud": null
    },
    "code": "ALGO",
    "rate": 0.4846365262289985,
    "volume": 773959989,
    "cap": 4021668802,
    "delta": {
      "hour": 1.0196,
      "day": 0.9109,
      "week": 1.6884,
      "month": 4.3464,
      "quarter": 4.0734,
      "year": 3.1474
    }
  },
  {
    "name": "Kaspa",
    "rank": 41,
    "age": 923,
    "color": "#74ccbc",
    "png32": "https://lcw.nyc3.cdn.digitaloceanspaces.com/production/currencies/32/kas.png",
    "png64": "https://lcw.nyc3.cdn.digitaloceanspaces.com/production/currencies/64/kas.png",
    "webp32": "https://lcw.nyc3.cdn.digitaloceanspaces.com/production/currencies/32/kas.webp",
    "webp64": "https://lcw.nyc3.cdn.digitaloceanspaces.com/production/currencies/64/kas.webp",
    "exchanges": 24,
    "markets": 32,
    "pairs": 9,
    "categories": [
      "smart_contract_platforms",
      "wallets"
    ],
    "allTimeHighUSD": 0.20762398728832757,
    "circulatingSupply": 25276993700,
    "totalSupply": 25276993700,
    "maxSupply": 28704026601,
    "links": {
      "website": "https://kaspa.org/",
      "whitepaper": "https://eprint.iacr.org/2018/104.pdf",
      "twitter": "https://x.com/KaspaCurrency",
      "reddit": "https://reddit.com/r/kaspa",
      "telegram": "https://t.me/Kaspaenglish",
      "discord": "https://discord.com/invite/kaspa",
      "medium": "https://medium.com/kaspa-currency",
      "instagram": "https://www.instagram.com/kaspa_currency/",
      "tiktok": null,
      "youtube": "https://www.youtube.com/@kaspaCurrency",
      "linkedin": "https://www.linkedin.com/company/kaspa-currency/",
      "twitch": null,
      "spotify": null,
      "naver": null,
      "wechat": null,
      "soundcloud": null
    },
    "code": "KAS",
    "rate": 0.15896526411318723,
    "volume": 341138387,
    "cap": 4018163979,
    "delta": {
      "hour": 1.0209,
      "day": 0.9821,
      "week": 1.0554,
      "month": 1.519,
      "quarter": 1.0812,
      "year": 1.1365
    }
  },
  {
    "name": "Immutable X",
    "rank": 42,
    "age": 1125,
    "color": "#13242c",
    "png32": "https://lcw.nyc3.cdn.digitaloceanspaces.com/production/currencies/32/_imx.png",
    "png64": "https://lcw.nyc3.cdn.digitaloceanspaces.com/production/currencies/64/_imx.png",
    "webp32": "https://lcw.nyc3.cdn.digitaloceanspaces.com/production/currencies/32/_imx.webp",
    "webp64": "https://lcw.nyc3.cdn.digitaloceanspaces.com/production/currencies/64/_imx.webp",
    "exchanges": 64,
    "markets": 78,
    "pairs": 14,
    "categories": [
      "smart_contract_platforms",
      "nfts",
      "gaming"
    ],
    "allTimeHighUSD": 9.49962548516342,
    "circulatingSupply": 1893437796,
    "totalSupply": 2000000000,
    "maxSupply": 2000000000,
    "links": {
      "website": "https://www.immutable.com",
      "whitepaper": "https://support.immutable.com/hc/en-us/articles/4405227590799",
      "twitter": "https://x.com/Immutable",
      "reddit": "https://reddit.com/r/ImmutableX",
      "telegram": "https://t.me/immutablex",
      "discord": "https://discord.com/invite/6GjgPkp464",
      "medium": "https://immutablex.medium.com/",
      "instagram": null,
      "tiktok": null,
      "youtube": null,
      "linkedin": null,
      "twitch": null,
      "spotify": null,
      "naver": null,
      "wechat": null,
      "soundcloud": null
    },
    "code": "_IMX",
    "rate": 2.070685929395652,
    "volume": 233630693,
    "cap": 3920715002,
    "delta": {
      "hour": 1.0279,
      "day": 0.9727,
      "week": 1.1922,
      "month": 1.9458,
      "quarter": 1.7481,
      "year": 1.4489
    }
  },
  {
    "name": "Cosmos",
    "rank": 43,
    "age": 2978,
    "color": "#30334c",
    "png32": "https://lcw.nyc3.cdn.digitaloceanspaces.com/production/currencies/32/atom.png",
    "png64": "https://lcw.nyc3.cdn.digitaloceanspaces.com/production/currencies/64/atom.png",
    "webp32": "https://lcw.nyc3.cdn.digitaloceanspaces.com/production/currencies/32/atom.webp",
    "webp64": "https://lcw.nyc3.cdn.digitaloceanspaces.com/production/currencies/64/atom.webp",
    "exchanges": 84,
    "markets": 170,
    "pairs": 62,
    "categories": [
      "smart_contract_platforms",
      "iot"
    ],
    "allTimeHighUSD": 44.477623439842205,
    "circulatingSupply": 390922431,
    "totalSupply": 390922431,
    "maxSupply": null,
    "links": {
      "website": "https://cosmos.network/",
      "whitepaper": "https://cosmos.network/resources/whitepaper",
      "twitter": "https://twitter.com/cosmos",
      "reddit": "https://reddit.com/r/cosmosnetwork",
      "telegram": "https://t.me/cosmosproject",
      "discord": "https://discord.com/invite/cosmosnetwork",
      "medium": null,
      "instagram": null,
      "tiktok": null,
      "youtube": null,
      "linkedin": null,
      "twitch": null,
      "spotify": null,
      "naver": null,
      "wechat": null,
      "soundcloud": null
    },
    "code": "ATOM",
    "rate": 9.813849859675429,
    "volume": 651201786,
    "cap": 3836454044,
    "delta": {
      "hour": 1.0223,
      "day": 1.0246,
      "week": 1.2052,
      "month": 2.477,
      "quarter": 2.5032,
      "year": 1.0022
    }
  },
  {
    "name": "Aave",
    "rank": 44,
    "age": 1513,
    "color": "#688cb5",
    "png32": "https://lcw.nyc3.cdn.digitaloceanspaces.com/production/currencies/32/aave.png",
    "png64": "https://lcw.nyc3.cdn.digitaloceanspaces.com/production/currencies/64/aave.png",
    "webp32": "https://lcw.nyc3.cdn.digitaloceanspaces.com/production/currencies/32/aave.webp",
    "webp64": "https://lcw.nyc3.cdn.digitaloceanspaces.com/production/currencies/64/aave.webp",
    "exchanges": 115,
    "markets": 218,
    "pairs": 51,
    "categories": [
      "lending",
      "governance",
      "yield_aggregators"
    ],
    "allTimeHighUSD": 663.2190116456594,
    "circulatingSupply": 15007425,
    "totalSupply": 16000000,
    "maxSupply": 16000000,
    "links": {
      "website": "https://aave.com/",
      "whitepaper": "https://docs.aave.com/hub/",
      "twitter": "https://x.com/AaveAave",
      "reddit": "https://reddit.com/r/Aave_Official",
      "telegram": "https://t.me/Aavesome",
      "discord": "https://discord.com/invite/aave",
      "medium": "https://medium.com/aave",
      "instagram": "https://instagram.com/aave.aave",
      "tiktok": null,
      "youtube": null,
      "linkedin": null,
      "twitch": null,
      "spotify": null,
      "naver": null,
      "wechat": null,
      "soundcloud": null
    },
    "code": "AAVE",
    "rate": 249.2392283841714,
    "volume": 2650782402,
    "cap": 3740439027,
    "delta": {
      "hour": 1.0125,
      "day": 1.0354,
      "week": 1.2156,
      "month": 1.8936,
      "quarter": 1.919,
      "year": 2.5389
    }
  },
  {
    "name": "Monero",
    "rank": 45,
    "age": 3850,
    "color": "#fc6404",
    "png32": "https://lcw.nyc3.cdn.digitaloceanspaces.com/production/currencies/32/xmr.png",
    "png64": "https://lcw.nyc3.cdn.digitaloceanspaces.com/production/currencies/64/xmr.png",
    "webp32": "https://lcw.nyc3.cdn.digitaloceanspaces.com/production/currencies/32/xmr.webp",
    "webp64": "https://lcw.nyc3.cdn.digitaloceanspaces.com/production/currencies/64/xmr.webp",
    "exchanges": 29,
    "markets": 59,
    "pairs": 19,
    "categories": [
      "privacy_coins"
    ],
    "allTimeHighUSD": 516.843201123428,
    "circulatingSupply": 18446744,
    "totalSupply": 18446744,
    "maxSupply": null,
    "links": {
      "website": "https://www.getmonero.org/",
      "whitepaper": "https://github.com/monero-project/research-lab/blob/master/whitepaper/whitepaper.pdf",
      "twitter": "https://twitter.com/monero",
      "reddit": "https://reddit.com/r/monero",
      "telegram": "https://t.me/bitmonero",
      "discord": null,
      "medium": null,
      "instagram": null,
      "tiktok": null,
      "youtube": null,
      "linkedin": null,
      "twitch": null,
      "spotify": null,
      "naver": null,
      "wechat": null,
      "soundcloud": null
    },
    "code": "XMR",
    "rate": 197.97240251457097,
    "volume": 2714765387,
    "cap": 3651946228,
    "delta": {
      "hour": 1.0422,
      "day": 1.0098,
      "week": 1.2645,
      "month": 1.2376,
      "quarter": 1.1448,
      "year": 1.1518
    }
  },
  {
    "name": "Celestia",
    "rank": 46,
    "age": 400,
    "color": "#7b2bfc",
    "png32": "https://lcw.nyc3.cdn.digitaloceanspaces.com/production/currencies/32/_tia.png",
    "png64": "https://lcw.nyc3.cdn.digitaloceanspaces.com/production/currencies/64/_tia.png",
    "webp32": "https://lcw.nyc3.cdn.digitaloceanspaces.com/production/currencies/32/_tia.webp",
    "webp64": "https://lcw.nyc3.cdn.digitaloceanspaces.com/production/currencies/64/_tia.webp",
    "exchanges": 29,
    "markets": 36,
    "pairs": 11,
    "categories": [
      "smart_contract_platforms",
      "governance"
    ],
    "allTimeHighUSD": 20.887498310853765,
    "circulatingSupply": 440650462,
    "totalSupply": 1087456438,
    "maxSupply": null,
    "links": {
      "website": "https://celestia.org/",
      "whitepaper": "https://docs.celestia.org/",
      "twitter": "https://twitter.com/CelestiaOrg",
      "reddit": "https://reddit.com/r/CelestiaNetwork",
      "telegram": "https://t.me/CelestiaCommunity",
      "discord": "https://discord.com/invite/YsnTPcSfWQ",
      "medium": null,
      "instagram": null,
      "tiktok": null,
      "youtube": "https://www.youtube.com/@CelestiaNetwork",
      "linkedin": null,
      "twitch": null,
      "spotify": null,
      "naver": null,
      "wechat": null,
      "soundcloud": null
    },
    "code": "_TIA",
    "rate": 8.198441224773076,
    "volume": 531943595,
    "cap": 3612646913,
    "delta": {
      "hour": 1.0228,
      "day": 1.0189,
      "week": 0.9892,
      "month": 1.9193,
      "quarter": 2.0005,
      "year": 0.7362
    }
  },
  {
    "name": "MANTRA DAO",
    "rank": 47,
    "age": 1569,
    "color": "#f99ec1",
    "png32": "https://lcw.nyc3.cdn.digitaloceanspaces.com/production/currencies/32/om.png",
    "png64": "https://lcw.nyc3.cdn.digitaloceanspaces.com/production/currencies/64/om.png",
    "webp32": "https://lcw.nyc3.cdn.digitaloceanspaces.com/production/currencies/32/om.webp",
    "webp64": "https://lcw.nyc3.cdn.digitaloceanspaces.com/production/currencies/64/om.webp",
    "exchanges": 26,
    "markets": 38,
    "pairs": 15,
    "categories": [
      "governance"
    ],
    "allTimeHighUSD": 4.479272534469675,
    "circulatingSupply": 863089961,
    "totalSupply": 888888887,
    "maxSupply": null,
    "links": {
      "website": "https://www.mantrachain.io/",
      "whitepaper": null,
      "twitter": "https://twitter.com/MANTRADAO",
      "reddit": null,
      "telegram": "https://t.me/MANTRA_omniverse",
      "discord": "https://discord.com/invite/2r6Sv93wQ3",
      "medium": "https://mantraomniverse.medium.com/",
      "instagram": "https://www.instagram.com/mantra_omniverse/",
      "tiktok": null,
      "youtube": "https://www.youtube.com/@MANTRAOMniverse",
      "linkedin": "https://www.linkedin.com/company/mantraomniverse/",
      "twitch": null,
      "spotify": null,
      "naver": null,
      "wechat": null,
      "soundcloud": null
    },
    "code": "OM",
    "rate": 4.048061815322674,
    "volume": 181723362,
    "cap": 3493841514,
    "delta": {
      "hour": 1.0279,
      "day": 1.05,
      "week": 1.1678,
      "month": 3.1444,
      "quarter": 4.3077,
      "year": 161.6312
    }
  },
  {
    "name": "Mantle",
    "rank": 48,
    "age": 506,
    "color": "#f1f1f1",
    "png32": "https://lcw.nyc3.cdn.digitaloceanspaces.com/production/currencies/32/______mnt.png",
    "png64": "https://lcw.nyc3.cdn.digitaloceanspaces.com/production/currencies/64/______mnt.png",
    "webp32": "https://lcw.nyc3.cdn.digitaloceanspaces.com/production/currencies/32/______mnt.webp",
    "webp64": "https://lcw.nyc3.cdn.digitaloceanspaces.com/production/currencies/64/______mnt.webp",
    "exchanges": 16,
    "markets": 52,
    "pairs": 18,
    "categories": [
      "governance"
    ],
    "allTimeHighUSD": 1.5048412868896262,
    "circulatingSupply": 3366841707,
    "totalSupply": 6219316794,
    "maxSupply": null,
    "links": {
      "website": "https://www.mantle.xyz/",
      "whitepaper": "https://docs.mantle.xyz/governance/introduction/overview",
      "twitter": "https://twitter.com/0xMantle",
      "reddit": null,
      "telegram": "https://t.me/mantlenetwork",
      "discord": "https://discord.com/invite/0xMantle",
      "medium": null,
      "instagram": null,
      "tiktok": null,
      "youtube": null,
      "linkedin": null,
      "twitch": null,
      "spotify": null,
      "naver": null,
      "wechat": null,
      "soundcloud": null
    },
    "code": "______MNT",
    "rate": 1.0312115328691858,
    "volume": 36762778,
    "cap": 3471925997,
    "delta": {
      "hour": 1.0351,
      "day": 1.0904,
      "week": 1.1944,
      "month": 1.8664,
      "quarter": 1.808,
      "year": 1.7648
    }
  },
  {
    "name": "Ondo",
    "rank": 49,
    "age": 319,
    "color": "#04040c",
    "png32": "https://lcw.nyc3.cdn.digitaloceanspaces.com/production/currencies/32/ondo.png",
    "png64": "https://lcw.nyc3.cdn.digitaloceanspaces.com/production/currencies/64/ondo.png",
    "webp32": "https://lcw.nyc3.cdn.digitaloceanspaces.com/production/currencies/32/ondo.webp",
    "webp64": "https://lcw.nyc3.cdn.digitaloceanspaces.com/production/currencies/64/ondo.webp",
    "exchanges": 27,
    "markets": 28,
    "pairs": 9,
    "categories": [
      "lending"
    ],
    "allTimeHighUSD": 1.9359468759707006,
    "circulatingSupply": 1953092719,
    "totalSupply": 10000000000,
    "maxSupply": 10000000000,
    "links": {
      "website": "https://ondo.foundation/",
      "whitepaper": "https://docs.ondo.finance/",
      "twitter": "https://twitter.com/ondofoundation",
      "reddit": null,
      "telegram": "https://t.me/ondocommunity",
      "discord": "https://discord.com/invite/YzhZaFbB92",
      "medium": null,
      "instagram": null,
      "tiktok": null,
      "youtube": null,
      "linkedin": null,
      "twitch": null,
      "spotify": null,
      "naver": null,
      "wechat": null,
      "soundcloud": null
    },
    "code": "ONDO",
    "rate": 1.7465039810304468,
    "volume": 765080562,
    "cap": 3411084209,
    "delta": {
      "hour": 1.0308,
      "day": 0.9897,
      "week": 1.634,
      "month": 2.896,
      "quarter": 3.0076,
      "year": null
    }
  },
  {
    "name": "Fantom",
    "rank": 50,
    "age": 2227,
    "color": "#1b6bfc",
    "png32": "https://lcw.nyc3.cdn.digitaloceanspaces.com/production/currencies/32/ftm.png",
    "png64": "https://lcw.nyc3.cdn.digitaloceanspaces.com/production/currencies/64/ftm.png",
    "webp32": "https://lcw.nyc3.cdn.digitaloceanspaces.com/production/currencies/32/ftm.webp",
    "webp64": "https://lcw.nyc3.cdn.digitaloceanspaces.com/production/currencies/64/ftm.webp",
    "exchanges": 91,
    "markets": 305,
    "pairs": 145,
    "categories": [
      "smart_contract_platforms"
    ],
    "allTimeHighUSD": 3.463518790484801,
    "circulatingSupply": 2803634835,
    "totalSupply": 3175000000,
    "maxSupply": 3175000000,
    "links": {
      "website": "https://fantom.foundation/",
      "whitepaper": "https://docs.fantom.foundation/",
      "twitter": "https://x.com/FantomFDN",
      "reddit": "https://reddit.com/r/FantomFoundation",
      "telegram": "https://t.me/Fantom_English",
      "discord": "https://discord.com/invite/zS4Ek4WByA/",
      "medium": "https://medium.com/fantomfoundation",
      "instagram": "https://www.instagram.com/official.fantom.foundation/",
      "tiktok": null,
      "youtube": null,
      "linkedin": null,
      "twitch": null,
      "spotify": null,
      "naver": null,
      "wechat": null,
      "soundcloud": null
    },
    "code": "FTM",
    "rate": 1.210644528685882,
    "volume": 843107158,
    "cap": 3394205173,
    "delta": {
      "hour": 1.0279,
      "day": 0.9797,
      "week": 1.1047,
      "month": 2.1934,
      "quarter": 3.1205,
      "year": 3.5755
    }
  }
]
